setup.py
simple_dependencies_manager.egg-info/PKG-INFO
simple_dependencies_manager.egg-info/SOURCES.txt
simple_dependencies_manager.egg-info/dependency_links.txt
simple_dependencies_manager.egg-info/requires.txt
simple_dependencies_manager.egg-info/top_level.txt
simple_manager/__init__.py
simple_manager/simple-manager.py
simple_manager/utils.py