Metadata-Version: 1.0
Name: simple-dependencies-manager
Version: 0.3.0
Summary: A simple script that helps you take control of your projects so you do not get crazy!
Home-page: http://github.com/victorpantoja/simple-dependencies-manager
Author: Victor Pantoja
Author-email: victor.pantoja@gmail.com
License: Apache License 2.0
Keywords: dependencies manager git tags requirements
Platform: UNKNOWN
Classifier: Development Status :: 4 - Beta
Classifier: Intended Audience :: Developers
Classifier: Programming Language :: Python
